src/__init__.py
src/hard_math.py
very_corp_internal_package-999999.0.1.dist-info/METADATA
very_corp_internal_package-999999.0.1.dist-info/WHEEL
very_corp_internal_package-999999.0.1.dist-info/licenses/LICENSE
very_corp_internal_package-999999.0.1.dist-info/RECORD
